<?xml version="1.0" encoding="UTF-8"?>
<text id="WB_KL-54">
    <metadata>
        <title>"Shinny Game Medicine"</title>
        <author>Mamie <alph>Offield</alph></author>
        <date>1957</date>
        <publication>William Bright, <em>The Karok Language</em> (1957), pp. 258-261, Text
            54</publication>
    </metadata>
    <data>
        <paragraph>
			<s>
				<kar> 
					<w>
						<m id= "1881">iknûumin veekxaréeyav</m>	
					</w>
					<w>
					<m id= "3409">itráhyar</m>
					</w>
					<w gl="his children">
					<m id= "4260">mu</m>
					<m id= "6132">túnviiv</m>
					<m id= "1369">hanik</m>
					</w>,
					<w gl="men">
					<m id= "833">ávans</m>
					<m id= "584">as</m>
					</w>
					<w>
					<m id= "3752">káru</m>	
					</w>
					<w>
						<m id= "7097"> yítha</m>	
					</w>
					<w>
						<m id= "656"> asiktávaan</m>	
					</w>.</kar>
				<eng>Burrill Peak Spirit had ten children, (nine) men and one woman.</eng>
			</s>
            <s>
                <kar>
                    <w>
			<m id="3748">kári xás</m>
			</w>
			<w gl="they said">
			<m id="3977">kun</m>
			<m id="4823">piip</m>
			</w>,
			<w>
			<m id="631">asaxêevar</m>
			
			</w>
			<w gl="its spirit">
			<m id="6376">v</m>
			<m id="2252">eekxaréeyav</m>	
			</w>,
			<w>
			<m id="6756">xákaan</m>	
			</w>
			<w>
			<m id="1144">chími</m>	
			</w>
			<w gl="they will play shinny">
					<m id= "3977">kun</m>
					<m id= "2520">imtháatv</m>
					<m id= "1379">eesh</m>
					</w>.</kar>
					<eng>And they said, Badly Peak Spirit (said), "Let's play shinny together!</eng>
			</s>
			 <s>
                <kar>
                    <w>
			<m id="7157">yukún</m>
			</w>
			<w>
			<m id="6307">úum</m>
			</w>			<w>
			<m id="3752">káru</m>
			</w>
			<w>
			<m id="2961">ishímfir</m>
			</w>,
			<w>
			<m id="631">asaxêevar</m>
			</w>
			<w gl="its spirit">
			<m id="6376">v</m>
			<m id="2252">eekxaréeyav</m>	
			</w>!</kar>
			<eng>You see, Badly Peak Spirit was tough too.</eng>
			</s>
			<s>
                <kar>
		   <w>
			<m id="3748">kári xás</m>
			</w>
			<w gl="the smallest">
			<m id="4407">pa</m>
			<m id="4353">niinamichtâapas</m>	
			</w>
			<w>
			<m id= "1881">iknûumin veekxaréeyav</m>	
			</w>
			<w gl="his child">
			<m id= "4407">pa</m>
			<m id= "4260">mú</m>
			<m id= "511">'arama</m>
			</w>
			<w>
			<m id="6383">vaa</m>
			</w>
			<w>
			<m id="6675">vúra</m>
			</w>
			<w gl="he grew up this way">
			<m id= "6175">u</m>
			<m id= "4004">kupa</m>
			<m id= "1453">'if</m>
			<m id= "1356">aha</m>
			</w>,
			<w gl="his hands">
			<m id= "4407">pa</m>
			<m id= "4260">mú</m>
			<m id= "6045">tiik</m>
			</w>
			<w gl="it was closed">
			<m id= "6175">u</m>
			<m id= "243">'ákchaak</m>
			<m id= "6035">tih</m>
			</w>,
			<w>
			<m id="6767">xákarari</m>
			</w>
			<w gl="his hands">
			<m id= "4407">pa</m>
			<m id= "4260">mú</m>
			<m id= "6045">tiik</m>
			</w>
			<w gl="it was closed">
			<m id= "6175">u</m>
			<m id= "243">'ákchaak</m>
			<m id= "6035">tih</m>
			</w>.</kar>
			<eng>And Burrill Peak Spirit's littlest child grew up this way, his hands were closed, both his hands were clo                         sed.</eng>
			</s>
			<s>
                <kar>
		  <w gl="underneath the ladder">
			<m id="6677">vuraakira</m>
			<m id="5478">súruk</m>	
			</w>
			 <w>
			<m id="6675">vúra</m>
			</w>
			<w gl="he stayed">
			<m id="6175">ú</m>
			<m id="1974">krii</m>	
			</w>.</kar>
			<eng>He stayed underneath the ladder (leading into the house).</eng>
			</s>
			<s>
                <kar>
		  <w gl="his dog">
			<m id="4260">mu</m>
			<m id="1175">chíshii</m>	
			</w>
			 <w>
			<m id="6675">vúra</m>
			</w>
			<w>
			<m id="6756">xákaan</m>
			</w>
			<w gl="they grew up">
			<m id="3977">kun</m>
			<m id="1640">'íifship</m>	
			</w>.</kar>
			<eng>He and his dog grew up together.</eng>
			</s>
			<s>
                 <kar>
		   <w>
		     <m id="3748">kári xás</m>
			</w>
			<w gl="they were covered with scabs">
			<m id="3977">kun</m>
			<m id="5149">púuxhi</m>
			<m id="6035">tih</m>
			</w>.</kar>
			<eng>And they were covered with scabs.</eng>
			</s>
			<s>
                 <kar>
		   <w>
		     <m id="3748">kári xás</m>
			</w>
			<w gl="the strongest">
			<m id="4407">p</m>
			<m id="1905">eekpihan</m>
			<m id="5522">tâapas</m>
			</w>
			<w>
			  <m id="6174">ta'ítam</m>
			</w>
			<w gl="he went off">
			<m id="6175">u</m>
			<m id="6396">vâaram</m>
			<m id="1378">aheen</m>
			</w>.</kar>
			<eng>So then the strongest one went off (to play).</eng>
			</s>
			<s>
                 <kar>
		   	<w>
			    <m id="631">asaxêevar</m>
			  </w>
			  <w gl="its spirit">
			<m id="6376">v</m>
			<m id="2252">eekxaréeyam</m>
			</w>
			<w gl="his child">
			<m id="4260">mú</m>
			<m id="511">'arama</m>
			</w>
			<w>
		     <m id= "6756">xákaan</m>	
			</w>
			<w>
		     <m id= "5562">tá</m>	
			</w>
			<w gl="they grabbed each other (preparatory to play)">
			<m id="3977">kun</m>
			<m id="1658">'îimasar</m>
			</w>.</kar>
			<eng>He and Baldy Peak Spirit's child grabbed each other (preparatory to play).</eng>
			</s>
			<s>
                 <kar>
		   <w>
		     <m id="3748">kári xás</m>
			</w>
			<w gl="he heard">
			<m id="6175">u</m>
			<m id="5954">thítiim</m>
			<m id="6035">tih</m>
			</w>,
			<w gl="underneath the ladder">
			<m id="4407">pa</m>
			<m id="6677">vuraakira</m>
			<m id="5478">súruk</m>
			</w>
			<w gl="sitting">
			<m id="1974">ikrêe</m>
			<m id="369">n</m>
			</w>
			<w gl="the smallest">
			<m id="4407">pa</m>
			<m id="4353">niinamichtâapas</m>
			</w>.</kar>
			<eng>And the littlest one, sitting underneath the ladder, heard it.</eng>
			</s>
			<s>
                 <kar>
		   <w>
		     <m id="3748">kári xás</m>
			</w>
			<w gl="he thought">
			<m id="6175">u</m>
			<m id="6939">xuus</m>
			</w>,
			<w>
			 <m id="4235">máva</m>
			  </w>
			  <w>
			 <m id="35">aaníhich</m>
			  </w>
			  <w>
			 <m id="5562">tá</m>
			  </w>
			  <w gl="they are beating him">
			<m id="3977">kun</m>
			<m id="1110">chífich</m>
			</w>.</kar>
			<eng>And he thought, "Look, big brother's getting beaten."</eng>
			</s>
			<s>
                 <kar>
		   <w>
		     <m id="3969">kúkuum</m>
			</w>
			<w>
		     <m id="6675">vúra</m>
			</w>
			<w>
		     <m id="7097">yítha</m>
			</w>
			<w gl="he went off">
			<m id="6175">u</m>
			<m id="6396">vâaram</m>
			</w>.</kar>
			<eng>Again one went off.</eng>
			</s>
			<s>
                 <kar>
		   <w>
		     <m id="1096">chavúra</m>
			</w>
			<w>
		     <m id="3930">koovúra</m>
			</w>
			<w>
		     <m id="5562">tá</m>
			</w>
			<w gl="they went">
			<m id="3977">kun</m>
			<m id="3496">ívyiihship</m>
			</w>.</kar>
			<eng>Finally they all went (and were beaten).</eng>
			</s>
			<s>
                 <kar>
		   <w>
		     <m id="4450">pácheech</m>
			</w>
			<w gl="he has">
			<m id="5562">t</m>
			<m id="6175">óo</m>
			</w>
			<w>
		        <m id="5206">saam</m>
			</w>.</kar>
			<eng>(The littlest one) remained alone.</eng>
			</s>
			<s>
                 <kar>
		   <w>
		     <m id="3748">kári xás</m>
			</w>
			<w gl="he thought">
			<m id="6175">u</m>
			<m id="6939">xus</m>
			</w>,
			<w>
		     <m id="1410">hûut</m>
			</w>
			<w gl="I will do">
			<m id="4349">ni</m>
			<m id="4014">kupheesh</m>
			</w>.</kar>
			<eng>And he thought, "What shall I do?"</eng>
			</s>
			<s>
			<kar>
			  <w>
			    <m id="3748">kári xás</m>
			     </w>
			     <w gl="his sister">
			<m id="4407">pa</m>
			<m id="4260">mu</m>
			<m id="4046">kústaan</m>
			</w>
			<w gl="he told">
			<m id="6175">u</m>
			<m id="2733">péer</m>
			</w>,
			<w>
			    <m id="1144">chími</m>
			     </w>
			     <w>
			    <m id="581">árus</m>
			     </w>
			     <w gl="weave">
			<m id="6545">vîik</m>
			<m id="1419">i</m>
			</w>.</kar>
				<eng>And he told his sister, "Weave seed-baskets.</eng>
			      </s>
			      <s>
			<kar>
			  <w>
			    <m id="864">áxak</m>
			     </w>
			     <w>
			    <m id="1729">ík</m>
			     </w>
			     <w gl="you will weave">
			<m id="4408">p</m>
			<m id="1418">ee</m>
			<m id="6545">vík</m>
			<m id="1379">eesh</m>
			</w>.</kar>
			<eng>You must weave two (of them)."</eng>
			      </s>
			      <s>
			<kar>
			  <w>
			    <m id="6174">ta'ítam</m>
			     </w>
			     <w gl="she wove them">
			<m id="6175">u</m>
			<m id="6545">vík</m>
			<m id="1378">aheen</m>
			</w>.</kar>
			<eng>So she wove them.</eng>
			      </s>
			      <s>
			<kar>
			  <w>
			    <m id="3748">kári xás</m>
			     </w>
			     <w gl="when she has">
			<m id="4408">pa</m>
			<m id="5562">t</m>
			<m id="6175">óo</m>
			</w>
			<w>
			    <m id="2845">pthith</m>
			     </w>,
			     <w>
			    <m id="3748">kári xás</m>
			     </w>
			     <w gl="she said">
			<m id="6175">u</m>
			<m id="4823">piip</m>
			</w>
			<w>
			    <m id="5562">tá</m>
			     </w>
			     <w gl="I finished weaving">
			<m id="4349">ní</m>
			<m id="2845">pthith</m>
			</w>.</kar>
			<eng>And when she finished weaving, then she said, "I've finished weaving."</eng>
			      </s>
			      <s>
			<kar>
			  <w>
			    <m id="3748">kári xás</m>
			     </w>
			     <w>
			    <m id="1192">chôora</m>
			     </w>,
			     <w>
			    <m id="1107">chémi</m>
			     </w>.</kar>
			     <eng>Then (he said), "All right, let's go!"</eng>
			      </s>
			      <s>
			<kar>
			  <w>
			    <m id="5562">tá</m>
			     </w>
			     <w gl="I bathe">
			<m id="4349">ni</m>
			<m id="4444">páatvar</m>
			</w>.</kar>
			<eng>I'm going to bathe.</eng>
			      </s>
			      <s>
			<kar>
			  <w>
			    <m id="6570">víri</m>
			     </w>
			     <w gl="when I come back out">
			<m id="4349">ni</m>
			<m id="2674">p</m>
			<m id="6450">váruprav</m>
			<m id="1358">ahaak</m>
			</w>,
			<w>
			  <m id="6383">vaa</m>
			     </w>
			     <w>
			  <m id="1729">i</m>
			     </w>
			     <w gl="with">
			<m id="3970">ku</m>
			<m id="4281">mûuk</m>
			</w>
			<w gl="I will cover">
			<m id="4349">nee</m>
			<m id="3329">thxúp</m>
			<m id="1379">eesh</m>
			</w>
			<w gl="the seed-basket">
			<m id="4407">pa</m>
			<m id="581">'árus</m>
			</w>.</kar>
			<eng>When I come back out (of the water), you must cover me with the seed-basket.</eng>
			      </s>
			      <s>
			<kar>
			  <w>
			    <m id="6174">ta'ítam</m>
			     </w>
			     <w gl="she covered">
			<m id="6175">u</m>
			<m id="3329">thxúp</m>
			<m id="1378">aheen</m>
			</w>.</kar>
			<eng>So she covered him.</eng>
			      </s>
			      <s>
			<kar>
			  <w>
			    <m id="3748">kári xás</m>
			     </w>
			     <w gl="when he took off">
			<m id="4408">p</m>
			<m id="6175">oo</m>
			<m id="2674">p</m>
			<m id="6334">ûusur</m>
			</w>,
			<w gl="the seed-basket">
			<m id="4407">pa</m>
			<m id="581">'árus</m>
			</w>,
			<w>
			    <m id="6174">ta'ítam</m>
			     </w>
			     <w gl="he stood still">
			<m id="6175">u</m>
			<m id="1617">hyárihishrih</m>
			<m id="1378">een</m>
			</w>.</kar>
			<eng>Then when he took off the seed-basket, he stood still.</eng>
			      </s>
			      <s>
			<kar>
			  <w>
			    <m id="6570">víri</m>
			     </w>
			     <w gl="his hair">
			<m id="4407">pa</m>
			<m id="4260">mu</m>
			<m id="1500">'ífuni</m>
			</w>
			<w>
			    <m id="1344">fúrax</m>
			     </w>
			     <w>
			    <m id="3809">kích</m>
			     </w>
			     <w gl="it was decorated">
			<m id="6175">u</m>
			<m id="5759">távahi</m>
			<m id="6035">tih</m>
			</w>.</kar>
			<eng>His hair was decorated on the ends with nothing but woodpecker heads.</eng>
			      </s>
			      <s>
			<kar>
			  <w>
			    <m id="3752">káru</m>
			     </w>
			     <w gl="his hands">
			<m id="4407">pa</m>
			<m id="4260">mú</m>
			<m id="6045">tiik</m>
			</w>
			<w>
			    <m id="7038">yánava</m>
			     </w>
			     <w>
			    <m id="3670">káan</m>
			     </w>
			      <w gl="his shinny-tossel">
			<m id="4407">pa</m>
			<m id="4260">mu</m>
			<m id="5583">tákasar</m>
			</w>.</kar>
			<eng>And there in his hands she saw his shinny-tossel.</eng>
			      </s>
			      <s>
			<kar>
			  <w>
			    <m id="7157">yukún</m>
			  </w>
			  <w>
			    <m id="6381">vaa</m>
			     </w>
			     <w>
			    <m id="6757">xákaan</m>
			     </w>
			     <w gl="he had grown up">
			<m id="6175">u</m>
			<m id="1640">'iifshípree</m>
			<m id="1369">nik</m>
			</w>,
			<w gl="his shinny-tossel">
			<m id="4407">pa</m>
			<m id="4260">mu</m>
			<m id="5583">tákasar</m>
			</w>.</kar>
			<eng>You see, he had grown up with that tossel.</eng>
			      </s>
			      <s>
			<kar>
			  <w>
			    <m id="3748">kári xás</m>
			  </w>
			  <w gl="his dog">
			<m id="4407">pa</m>
			<m id="4260">mu</m>
			<m id="1175">chíshii</m>
			</w>
			<w>
			    <m id="6174">ta'ítam</m>
			  </w>
			  <w>
			    <m id="6235">úmpaan</m>
			  </w>
			  <w gl="it dived into the water">
			<m id="6174">u</m>
			<m id="1691">iipkúrih</m>
			<m id="1378">een</m>
			</w>.</kar>
			<eng>So then his dog dived into the water.</eng>
			      </s>
			      <s>
			<kar>
			  <w>
			    <m id="6174">ta'ítam</m>
			  </w>
			  <w gl="when it came back up">
			<m id="4408">p</m>
			<m id="6175">oo</m>
			<m id="2674">p</m>
			<m id="6450">váruprav</m>
			</w>
			<w>
			    <m id="6174">ta'ítam</m>
			  </w>
			  <w gl="it shook itself">
			<m id="6175">u</m>
			<m id="5062">piythúfrih</m>
			<m id="1378">een</m>
			</w>.</kar>
			<eng>When it came back up, it shook itself.</eng>
			      </s>
			      <s>
			<kar>
			  <w>
			    <m id="6174">ta'ítam</m>
			  </w>
			  <w gl="they covered">
			<m id="3997">kun</m>
			<m id="3329">ithxúp</m>
			<m id="1378">aheen</m>
			</w>
			<w gl="the seed-basket">
			<m id="4407">pa</m>
			<m id="581">'árus</m>
			</w>
			<w>
			    <m id="4281">mûuk</m>
			  </w>.</kar>
			<eng>Then they covered it with the seed-basket.</eng>
			      </s>
			      <s>
			<kar>
			  <w>
			    <m id="6570">víri</m>
			  </w>
			  <w gl="when they took it off">
			<m id="4408">pa</m>
			<m id="3997">kun</m>
			<m id="2674">p</m>
			<m id="6334">ûusur</m>
			</w>
			<w>
			    <m id="1344">fúrax</m>
			  </w>
			  <w>
			    <m id="3809">kích</m>
			  </w>
			  <w gl="it was decorated">
			<m id="6175">u</m>
			<m id="5759">távahi</m>
			<m id="6035">ti</m>
			</w>
			<w gl="the ends of its (the dog's) hair">
			<m id="4407">pa</m>
			<m id="4260">mu</m>
			<m id="1500">'ifunih</m>
			<m id="2697">'ípan</m>
			</w>.</kar>
		<eng>When they took it off, the ends of (the dog's) hair were decorated with nothing but woodepecker scalps.</eng>
			      </s>
			      <s>
			<kar>
			  <w>
			    <m id="3748">kári xás</m>
			  </w>
			  <w gl="he said">
			<m id="6175">u</m>
			<m id="4823">piip</m>
			</w>,
			<w>
			    <m id="1192">chôora</m>
			  </w>
			  <w>
			    <m id="1107">chémi</m>
			  </w>.</kar>
		<eng>Then he said, "All right, let's go.</eng>
			      </s>
			       <s>
			<kar>
			  <w>
			    <m id="6174">ta'ítam</m>
			  </w>
			  <w gl="she grappled with">
			<m id="6175">u</m>
			<m id="1658">'îimasar</m>
			<m id="1378">aheen</m>
			</w>
			<w>
			    <m id="631">asaxêevar</m>
			  </w>
			  <w gl="its spirit">
			<m id="6376">v</m>
			<m id="2252">eekxaréeyav</m>
			</w>
			<w>
			    <m id="6757">xákaan</m>
			  </w>.</kar>
		<eng>So she grappled with Baldy Peak Spirit.</eng>
			      </s>
			      <s>
			<kar>
			  <w>
			    <m id="6570">víri</m>
			  </w>
			  <w gl="when he tossed">
			<m id="4408">p</m>
			<m id="6175">oo</m>
			<m id="5533">tâat</m>
			<m id="5417">si</m>
			</w>
			<w gl="his tossel">
			<m id="4407">pa</m>
			<m id="4260">mu</m>
			<m id="5583">tákasar</m>
			</w>
			<w>
			    <m id="7037">yá</m>
			  </w>
			  <w>
			    <m id="3753">káruk</m>
			  </w>
			  <w>
			    <m id="3264">ithivthaneen'ípan</m>
			  </w>
			  <w gl="it landed">
			<m id="6175">u</m>
			<m id="2167">kúuyva</m>
			</w>.</kar>
		<eng>When he tossed his tossel, he saw it landed at the upriver end of the world.</eng>
			      </s>
			      <s>
			<kar>
			  <w>
			    <m id="6174">ta'ítam</m>
			  </w>
			  <w gl="it ran off">
			<m id="6175">u</m>
			<m id="2212">kvíripshur</m>
			<m id="1378">aheen</m>
			</w>
			<w gl="his dog">
			<m id="4407">pa</m>
			<m id="4260">mu</m>
			<m id="1175">chíshiih</m>
			</w>.</kar>
		<eng>So his dog ran off.</eng>
			      </s>
			      <s>
			<kar>
			  <w>
			    <m id="6174">ta'ítam</m>
			  </w>
			  <w gl="it brought back">
			<m id="6175">u</m>
			<m id="2674">p</m>
			<m id="3319">ithvúk</m>
			<m id="1378">aheen</m>
			</w>
			<w gl="the tossel">
			<m id="4407">pa</m>
			<m id="5583">tákasar</m>
			</w>.</kar>
		<eng>And it brought the tossel back.</eng>
			      </s>
			      <s>
			<kar>
			  <w>
			    <m id="6174">ta'ítam</m>
			  </w>
			  <w>
			    <m id="3969">kúkuum</m>
			  </w>
			  <w gl="they grappled">
			<m id="3997">kun</m>
			<m id="1658">'îimasar</m>
			<m id="1378">aheen</m>
			</w>.</kar>
		<eng>So they grappled again.</eng>
			      </s>
			      <s>
			<kar>
			  <w>
			    <m id="7037">yá</m>
			  </w>
			  <w>
			    <m id="7212">yúruk</m>
			  </w>
			  <w>
			    <m id="3264">ithivthaneen'ípan</m>
			  </w>
			  <w>
			    <m id="3978">kúna</m>
			  </w>
			  <w gl="it lands">
			<m id="6175">u</m>
			<m id="2167">kúuyva</m>
			</w>
			<w gl="the tossel">
			<m id="4407">pa</m>
			<m id="5583">tákasar</m>
			</w>.</kar>
		<eng>He saw the tossel land in turn at the downriver end of the world.</eng>
			      </s>
			      <s>
			<kar>
			  <w>
			    <m id="7157">yukún</m>
			  </w>
			  <w>
			    <m id="6307">uum</m>
			  </w>
			  <w gl="real spirit person">
			<m id="2252">ikxareeyaa</m>
			<m id="5522">tâapas</m>
			</w>
			<w gl="he had grown up">
			<m id="6175">u</m>
			<m id="1640">'iifshípree</m>
			<m id="1369">nik</m>
			</w>
			 <w>
			    <m id="1881">iknûumin veekxaréeyav</m>
			  </w>.</kar>
		<eng>You see, Burrill Peak Spirit had grown up into a real ikxaréeyav.</eng>
			      </s>
			      <s>
			<kar>
			  <w>
			    <m id="7157">yukú</m>
			  </w>
			   <w>
			    <m id="4299">naa</m>
			  </w>
			  <w>
			    <m id="1729">í</m>
			  </w>
			  <w>
			    <m id="3752">káru</m>
			  </w>
			  <w>
			    <m id="6381">vaa</m>
			  </w>
			  <w gl="I will do">
			<m id="4349">ni</m>
			<m id="4014">kupheesh</m>
			</w>
			<w gl="as he did">
			<m id="4408">p</m>
			<m id="6175">oo</m>
			<m id="4086">kúphaa</m>
			<m id="1369">nik</m>
			</w>
			<w gl="the Burrill Peak Spirit">
			<m id="4407">p</m>
			<m id="1881">eeknûumin veekxaréeyav</m>
			</w>.</kar>
		<eng>You see, I must also do that way, as Burrill Peak Spirit did.</eng>
			      </s>
		
		</paragraph>
	</data>
</text>
				
				
				
					
					
				